setup.py
amaze/__init__.py
amaze/disjointsets.py
amaze/generate.py
amaze/kruskal.py
amaze/maze.py
amaze/recursive.py
amaze/runner.py
amaze/demo/__init__.py
amaze/demo/tkdemo.py
nathan_test.egg-info/PKG-INFO
nathan_test.egg-info/SOURCES.txt
nathan_test.egg-info/dependency_links.txt
nathan_test.egg-info/entry_points.txt
nathan_test.egg-info/top_level.txt