Metadata-Version: 1.0
Name: nathan-test
Version: 0.2
Summary: Haze generation
Home-page: UNKNOWN
Author: Nitin Ware
Author-email: nitinware@gmail.com
License: UNKNOWN
Platform: UNKNOWN
